design.sv
 `timescale 1ns / 1ns 

 module Divide(  
   input      clk,  
       input                     reset,  
   input      start,  
   input [7:0]  A,  
   input [7:0]  B,  
   output [7:0]  Q,  
   output [7:0]  R,  
   output     ok ,   // =1 when ready to get the result   
       output err  
   );  
   reg       active;   // True if the divider is running  
   reg [4:0]    cycle;   // Number of cycles to go  
   reg [7:0]   result;   // Begin with A, end with Q  
   reg [7:0]   div;   // Divisor 
   reg [7:0]   work;    // Running R  
   // Calculate the current digit  
   wire [8:0]   sub = { work[6:0], result[7] } - div;  
       assign err = !B;  
   // Send the results to our master  
   assign Q = result;  
   assign R = work;  
   assign ok = ~active;
    
   // The state machine  
   always @(posedge clk,posedge reset) begin  
    
     if (reset) begin  
       active <= 0;  
       cycle <= 0;  
       result <= 0;  
       div <= 0;  
       work <= 0;  
     end  
     else if(start) begin  
       if (active) begin  
         // Run an iteration of the divider.  
         if (sub[8] == 0) begin  
           work <= sub[7:0];  
           result <= {result[6:0], 1'b1};  
         end  
         else begin  
           work <= {work[6:0], result[7]};  
           result <= {result[6:0], 1'b0};  
         end  
         if (cycle == 0) begin  
           active <= 0;  
         end  
         cycle <= cycle - 5'd1;  
       end  
       else begin  
         // Set up for an unsigned divider.  
         cycle <= 5'd7;  
         result <= A;  
         div <= B;  
         work <= 8'b0;  
         active <= 1;  
       end  
     end  
   end  
 endmodule

testbench.sv
 `timescale 1ns / 1ns  

 module tb_divider;  
      // Inputs  
      reg clock;  
      reg reset;  
      reg start;  
   reg [7:0] A;  
   reg [7:0] B;  
      // Outputs  
   wire [7:0] Q;  
   wire [7:0] R;  
      wire ok;  
      wire err;  
      // Instantiate the Unit Under Test (UUT)  
      Divide uut (  
           .clk(clock),   
           .start(start),  
           .reset(reset),  
           .A(A),   
           .B(B),   
        .Q(Q),   
           .R(R),   
           .ok(ok),  
           .err(err)  
      );  
      initial begin   
            clock = 0;  
            forever #50 clock = ~clock;  
      end  
      initial begin  
        $dumpfile("dump.vcd");
        $dumpvars(1,tb_divider);
           // Initialize Inputs  
           start = 0;  
           A = 8'd64;  
           B = 8'd10;  
           reset=1;  
           // Wait 100 ns for global reset to finish  
           #1000;  
           reset=0;  
     start = 1;   
           #900;  
           $finish;  
      end  
 endmodule

dump.vcd
$date
	Fri Mar 29 06:50:32 2019
$end
$version
	Icarus Verilog
$end
$timescale
	1ns
$end
$scope module tb_divider $end
$var wire 1 ! ok $end
$var wire 1 " err $end
$var wire 8 # R [7:0] $end
$var wire 8 $ Q [7:0] $end
$var reg 8 % A [7:0] $end
$var reg 8 & B [7:0] $end
$var reg 1 ' clock $end
$var reg 1 ( reset $end
$var reg 1 ) start $end
$upscope $end
$enddefinitions $end
#0
$dumpvars
0)
1(
0'
b1010 &
b1000000 %
b0 $
b0 #
0"
1!
$end
#50
1'
#100
0'
#150
1'
#200
0'
#250
1'
#300
0'
#350
1'
#400
0'
#450
1'
#500
0'
#550
1'
#600
0'
#650
1'
#700
0'
#750
1'
#800
0'
#850
1'
#900
0'
#950
1'
#1000
0'
1)
0(
#1050
0!
b1000000 $
1'
#1100
0'
#1150
b10000000 $
1'
#1200
0'
#1250
b0 $
b1 #
1'
#1300
0'
#1350
b10 #
1'
#1400
0'
#1450
b100 #
1'
#1500
0'
#1550
b1000 #
1'
#1600
0'
#1650
b1 $
b110 #
1'
#1700
0'
#1750
b11 $
b10 #
1'
#1800
0'
#1850
1!
b110 $
b100 #
1'
